.pylintrc
.travis.yml
AUTHORS
CONTRIBUTING.rst
ChangeLog
LICENSE
MANIFEST.in
README.rst
run_tests.sh
setup.cfg
setup.py
tox.ini
bin/ryu
bin/ryu-manager
debian/changelog
debian/clean
debian/compat
debian/control
debian/copyright
debian/docs
debian/log.conf
debian/python-ryu-doc.doc-base
debian/python-ryu-doc.docs
debian/python-ryu.install
debian/rules
debian/ryu-bin.dirs
debian/ryu-bin.install
debian/ryu-bin.manpages
debian/ryu-bin.postrm
debian/ryu-bin.ryu.logrotate
debian/ryu-bin.ryu.upstart
debian/ryu.conf
debian/source/format
doc/Makefile
doc/source/api_ref.rst
doc/source/app.rst
doc/source/components.rst
doc/source/conf.py
doc/source/configuration.rst
doc/source/developing.rst
doc/source/docutils.conf
doc/source/getting_started.rst
doc/source/gui.png
doc/source/gui.rst
doc/source/index.rst
doc/source/library.rst
doc/source/library_bgp_speaker.rst
doc/source/library_bgp_speaker_ref.rst
doc/source/library_mrt.rst
doc/source/library_of_config.rst
doc/source/library_ovsdb_manager.rst
doc/source/library_packet.rst
doc/source/library_packet_ref.rst
doc/source/library_pcap.rst
doc/source/nicira_ext_ref.rst
doc/source/ofproto_base.rst
doc/source/ofproto_ref.rst
doc/source/ofproto_v1_0_ref.rst
doc/source/ofproto_v1_2_ref.rst
doc/source/ofproto_v1_3_ref.rst
doc/source/ofproto_v1_4_ref.rst
doc/source/ofproto_v1_5_ref.rst
doc/source/parameters.rst
doc/source/ryu_app_api.rst
doc/source/snort_integrate.rst
doc/source/test-of-config-with-linc.rst
doc/source/test-vrrp.rst
doc/source/tests.rst
doc/source/tls.rst
doc/source/using_with_openstack.rst
doc/source/writing_ryu_app.rst
doc/source/_static/.placeholder
doc/source/_templates/.placeholder
doc/source/app/ofctl.rst
doc/source/app/ofctl_rest.rst
doc/source/app/rest_vtep.rst
doc/source/library_packet_ref/packet_arp.rst
doc/source/library_packet_ref/packet_base.rst
doc/source/library_packet_ref/packet_bfd.rst
doc/source/library_packet_ref/packet_bgp.rst
doc/source/library_packet_ref/packet_bmp.rst
ryu.egg-info/PKG-INFO
ryu.egg-info/SOURCES.txt
ryu.egg-info/dependency_links.txt
ryu.egg-info/entry_points.txt
ryu.egg-info/not-zip-safe
ryu.egg-info/pbr.json
ryu.egg-info/requires.txt
ryu.egg-info/top_level.txt
