Metadata-Version: 1.1
Name: ryu
Version: 4.20
Summary: Component-based Software-defined Networking Framework
Home-page: http://osrg.github.io/ryu/
Author: Ryu project team
Author-email: ryu-devel@lists.sourceforge.net
License: Apache License 2.0
Keywords: openflow
Platform: any
Classifier: Development Status :: 5 - Production/Stable
Classifier: License :: OSI Approved :: Apache Software License
Classifier: Topic :: System :: Networking
Classifier: Natural Language :: English
Classifier: Programming Language :: Python
Classifier: Programming Language :: Python :: 2.7
Classifier: Programming Language :: Python :: 3
Classifier: Programming Language :: Python :: 3.4
Classifier: Operating System :: Unix
